setup.py
flux/__init__.py
flux/__version__.py
flux/current_timeline.py
flux/gevent_timeline.py
flux/sequence.py
flux/timeline.py
flux.egg-info/PKG-INFO
flux.egg-info/SOURCES.txt
flux.egg-info/dependency_links.txt
flux.egg-info/namespace_packages.txt
flux.egg-info/top_level.txt