Metadata-Version: 1.1
Name: flux
Version: 1.3.4
Summary: Artificial time library
Home-page: UNKNOWN
Author: Rotem Yaari
Author-email: vmalloc@gmail.com
License: BSD
Platform: UNKNOWN
Classifier: Programming Language :: Python :: 2.6
Classifier: Programming Language :: Python :: 2.7
Classifier: Programming Language :: Python :: 3.3
Classifier: Programming Language :: Python :: 3.4
Classifier: Programming Language :: Python :: 3.5
